demo/data/__init__.py
kochat/__init__.py
kochat/decorators.py
kochat/app/__init__.py
kochat/app/kochat_api.py
kochat/app/scenario.py
kochat/app/scenario_manager.py
kochat/data/__init__.py
kochat/data/dataset.py
kochat/data/organizer.py
kochat/data/preprocessor.py
kochat/loss/__init__.py
kochat/loss/base_loss.py
kochat/loss/center_loss.py
kochat/loss/coco_loss.py
kochat/loss/cosface.py
kochat/loss/crf_loss.py
kochat/loss/cross_entropy_loss.py
kochat/loss/gaussian_mixture.py
kochat/loss/masking.py
kochat/loss/utils/__init__.py
kochat/loss/utils/masking.py
kochat/model/__init__.py
kochat/model/base/__init__.py
kochat/model/base/convolution.py
kochat/model/embed/__init__.py
kochat/model/embed/fasttext.py
kochat/model/embed/word2vec.py
kochat/model/entity/__init__.py
kochat/model/entity/lstm.py
kochat/model/intent/__init__.py
kochat/model/intent/cnn.py
kochat/model/intent/lstm.py
kochat/model/layers/__init__.py
kochat/model/layers/convolution.py
kochat/proc/__init__.py
kochat/proc/base_processor.py
kochat/proc/distance_classifier.py
kochat/proc/distance_estimator.py
kochat/proc/entity_recognizer.py
kochat/proc/fallback_detector.py
kochat/proc/gensim_embedder.py
kochat/proc/intent_classifier.py
kochat/proc/sklearn_processor.py
kochat/proc/softmax_classifier.py
kochat/proc/torch_processor.py
kochat/proc/utils/__init__.py
kochat/proc/utils/metrics.py
kochat/proc/utils/visualizer.py
kochat/utils/__init__.py
kochat/utils/metrics.py
kochat/utils/visualizer.py
kochat-1.0.3.dist-info/LICENSE
kochat-1.0.3.dist-info/METADATA
kochat-1.0.3.dist-info/WHEEL
kochat-1.0.3.dist-info/top_level.txt
kochat-1.0.3.dist-info/RECORD
